__init__.py
api.py
cli_demo.py
cli_demo_vision.py
utils.py
web_demo.py
web_demo2.py
web_demo_old.py
web_demo_vision.py
ptuning/__init__.py
ptuning/arguments.py
ptuning/main.py
ptuning/trainer.py
ptuning/trainer_seq2seq.py
ptuning/web_demo.py
chatglm6bpkg-0.0.1.dist-info/METADATA
chatglm6bpkg-0.0.1.dist-info/WHEEL
chatglm6bpkg-0.0.1.dist-info/licenses/LICENSE
chatglm6bpkg-0.0.1.dist-info/RECORD
