Metadata-Version: 2.1
Name: ChatGLM6Bpkg
Version: 0.0.1
Summary: ChatGLM6Bpkg is a package for ChatGLM-6B (https://github.com/THUDM/ChatGLM-6B/tree/main).
Project-URL: Homepage, https://github.com/thu-coai/ChatGLM6Bpkg/tree/main
Author-email: Yilin Niu <niuyl14@tsinghua.org.cn>
License:                                  Apache License
License-File: LICENSE
Classifier: License :: OSI Approved :: MIT License
Classifier: Operating System :: OS Independent
Classifier: Programming Language :: Python :: 3
Requires-Python: >=3.9
Requires-Dist: accelerate
Requires-Dist: cpm-kernels
Requires-Dist: datasets
Requires-Dist: fastapi
Requires-Dist: gradio
Requires-Dist: jieba
Requires-Dist: mdtex2html
Requires-Dist: nltk
Requires-Dist: protobuf
Requires-Dist: rouge-chinese
Requires-Dist: sentencepiece
Requires-Dist: torch>=1.10
Requires-Dist: transformers==4.27.1
Requires-Dist: uvicorn
